{"editor":null,"atualizationDateTime":null,"publicationDateTime":"23\/08\/2016 07h03","author":"Da Agência Ansa Brasil","links":[],"id":"node-1039730","title":"Tufão atinge Tóquio e deixa pelo menos dois mortos","paragraphs":["O tufão Mindulle, o nono da estação na Ásia, atingiu a cidade de Tóquio, no Japão, nessa segunda-feira (22) e deixou pelo menos dois mortos, segundo a imprensa local. As informações são da Agência Ansa. A agência meteorológica japonesa lançou alertas sobre as potentes rajadas de vento e chuvas torrenciais, além da possibilidade de evacuação em algumas regiões da capital. Mais de 420 voos foram cancelados pelas companhias aéreas, a maioria da Japan Airlines e da All Nippon Airwais."],"category":"Internacional","url":"\/internacional\/noticia\/2016-08\/tufao-atinge-toquio-e-deixa-pelo-menos-dois-mortos","local":"Roma","tags":["Japão","tufão","mortos"]}