{"editor":"Nádia Franco","atualizationDateTime":null,"publicationDateTime":"13\/08\/2016 23h57","author":"Karine Melo \u2013 Repórter da Agência Brasil","links":[],"id":"node-1037557","title":"Phelps despede-se das piscinas com quinto ouro nos Jogos do Rio","paragraphs":["Michael Phelps com a medalha de ouro pelo 4x100 m medleyReuters\/Marcos Brindicci\/Direitos Reservados","Com direito a recorde olímpico \u2013 3min29s34 \u2013, o norte-americano Michael Phelps despediu-se das piscinas no Estádio Aquático do Rio com a 23ª medalha de ouro de sua carreira na prova de revezamento 4x100m medley na noite deste sábado (13) . O ouro desta noite foi o quinto conquistado por Phelps nos Jogos Olímpicos Rio 2016. Terceiro a entrar na piscina, Phelps tirou a equipe da segunda posição. A medalha de prata ficou com a Grã-Bretanha, com 3 min29s24, e a de bronze, com a Austrália, que terminou a competição com a marca de 3min29s93.","Na mesma prova. a equipe brasileira, composta por Guilherme Guido, Felipe França, Henrique Martins e Marcelo Chierighini, fez o sétimo tempo, mas, a com a desclassificação da China, passou para a sexta colocação, com tempo de 3min32s84."],"category":"Rio 2016","url":"\/rio-2016\/noticia\/2016-08\/phelps-despede-se-das-piscinas-com-quinto-ouro-nos-jogos-do-rio","local":"Rio de Janeiro","tags":["Rio 2016","natação","revezamento 4x100m medley","Michael Phelps"]}