{"editor":"Juliana Andrade","atualizationDateTime":null,"publicationDateTime":"08\/08\/2016 12h51","author":"Paula Laboissière - Repórter da Agência Brasil","links":["http:\/\/www.ebc.com.br\/esportes\/rio-2016\/2016\/08\/acompanhe-o-que-acontece-nesta-segunda-nos-jogos-olimpicos"],"id":"node-1035810","title":"Judoca Rafaela Silva vence e avança para a semifinal","paragraphs":["A judoca brasileira Rafaela Silva venceu a húngara Hedvig Karakas nas quartas de finalReuters\/Toru Hanai\/Direitos Reservados","A judoca brasileira Rafaela Silva venceu hoje (8) a húngara Hedvig Karakas nas quartas de final e segue para a disputa da semifinal na categoria até 57 quilos feminino. Rafaela conseguiu um wazari sobre a oponente e encara, hoje à tarde, a romena Corina Caprioriu. Se vencer, a brasileira vai disputar a medalha de ouro.","Mais cedo, a brasileira venceu a alemã Myriam Roper com um ippon e a sul-coreana Kim Jandi com um wazari.",">> Acompanhe  aqui a Rio 2016"],"category":"Rio 2016","url":"\/rio-2016\/noticia\/2016-08\/judoca-rafaela-silva-vence-e-avanca-para-semifinal","local":"Brasília","tags":["Rio 2016","Judô","Rafaela Silva vence e avança para semifinal"]}